{
  "name": "megamenu",
  "type": "header",
  "sections": {
    "topmenu": {
      "type": "topmenu",
      "settings": {
        "text-announcement": "Buy 1 get 1 50% off almost everything!",
        "link-announcement": "shopify:\/\/collections\/all",
        "text-support": "Customer Support",
        "link-support": "shopify:\/\/pages\/contact"
      }
    },
    "header": {
      "type": "header",
      "blocks": {
        "0e43c862-98f9-4d47-be3c-fecbeec06c26": {
          "type": "navigation",
          "settings": {
            "text-navigation": "Shop All",
            "link-nav-test": "shop-all",
            "color-fill": "#7197c3",
            "link-img": "https:\/\/cdn.shopify.com\/s\/files\/1\/0721\/9979\/9103\/files\/f3815c86889deba19e5df1db73f5f625.webp?v=1677138096",
            "link-img-nav": "https:\/\/cdn.shopify.com\/s\/files\/1\/0721\/9979\/9103\/files\/f3815c86889deba19e5df1db73f5f625.webp?v=1677138096"
          }
        },
        "af8bcc0f-3ec2-4036-a4ad-c5f90ccfb125": {
          "type": "navigation",
          "settings": {
            "text-navigation": "Girls",
            "link-nav-test": "main-menu",
            "color-fill": "#e7c5cc",
            "link-img": "https:\/\/cdn.shopify.com\/s\/files\/1\/0721\/9979\/9103\/files\/Frame_69.png?v=1677123594",
            "link-img-nav": "add link img"
          }
        },
        "92dc4dde-e862-47fc-869d-7c9ed4716a06": {
          "type": "navigation",
          "settings": {
            "text-navigation": "Boys",
            "link-nav-test": "",
            "color-fill": "#c6e0f2",
            "link-img": "add link img",
            "link-img-nav": "add link img"
          }
        },
        "4cf94ef8-c1d9-46a4-8064-b29a23e08ac5": {
          "type": "navigation",
          "settings": {
            "text-navigation": "School",
            "link-nav-test": "shop-all",
            "color-fill": "#db806b",
            "link-img": "add link img",
            "link-img-nav": "add link img"
          }
        },
        "8f3c42f8-9b97-4169-9727-23e392ac14f9": {
          "type": "navigation",
          "settings": {
            "text-navigation": "Brands",
            "link-nav-test": "shop-all",
            "color-fill": "#afa2da",
            "link-img": "add link img",
            "link-img-nav": "add link img"
          }
        },
        "1b46a341-ef89-4a8a-b51d-4b3d2e49ab3b": {
          "type": "navigation",
          "settings": {
            "text-navigation": "Sale",
            "link-nav-test": "",
            "color-fill": "#ec273c",
            "link-img": "add link img",
            "link-img-nav": "add link img"
          }
        },
        "2675c809-dbc8-4909-8aa2-be0aa939fdda": {
          "type": "navigation",
          "settings": {
            "text-navigation": "Discover",
            "link-nav-test": "",
            "color-fill": "#efd1a0",
            "link-img": "add link img",
            "link-img-nav": "add link img"
          }
        }
      },
      "block_order": [
        "0e43c862-98f9-4d47-be3c-fecbeec06c26",
        "af8bcc0f-3ec2-4036-a4ad-c5f90ccfb125",
        "92dc4dde-e862-47fc-869d-7c9ed4716a06",
        "4cf94ef8-c1d9-46a4-8064-b29a23e08ac5",
        "8f3c42f8-9b97-4169-9727-23e392ac14f9",
        "1b46a341-ef89-4a8a-b51d-4b3d2e49ab3b",
        "2675c809-dbc8-4909-8aa2-be0aa939fdda"
      ],
      "settings": {
        "color_scheme": "background-1",
        "logo_position": "middle-left",
        "menu": "main-menu",
        "menu_type_desktop": "mega",
        "sticky_header_type": "on-scroll-up",
        "show_line_separator": true,
        "mobile_logo_position": "center",
        "text-pickup": "In-store pickup:",
        "nav-url": "",
        "pickup-button": "Select store",
        "pickup-link": "",
        "margin_bottom": 0,
        "padding_top": 20,
        "padding_bottom": 20
      }
    }
  },
  "order": [
    "topmenu",
    "header"
  ]
}
